[
  {
    "number": 25,
    "result": "N/A",
    "record": "N/A",
    "opponent": "Kubrat Pulev",
    "type": "N/A",
    "round": "– (12)",
    "date": "20 Jun 2020",
    "location": "Tottenham Hotspur Stadium, London, England",
    "notes": "Defending WBA (Super), IBF, WBO, and IBO heavyweight titles"
  },
  {
    "number": 24,
    "result": "Win",
    "record": "23–1",
    "opponent": "Andy Ruiz Jr.",
    "type": "UD",
    "round": "12",
    "date": "7 Dec 2019",
    "location": "Diriyah Arena, Diriyah, Saudi Arabia",
    "notes": "Won WBA (Super), IBF, WBO, and IBO heavyweight titles"
  },
  {
    "number": 23,
    "result": "Loss",
    "record": "22–1",
    "opponent": "Andy Ruiz Jr.",
    "type": "TKO",
    "round": "7 (12), 1:33",
    "date": "1 Jun 2019",
    "location": "Madison Square Garden, New York City, New York, US",
    "notes": "Lost WBA (Super), IBF, WBO, and IBO heavyweight titles"
  },
  {
    "number": 22,
    "result": "Win",
    "record": "22–0",
    "opponent": "Alexander Povetkin",
    "type": "TKO",
    "round": "7 (12), 1:59",
    "date": "22 Sep 2018",
    "location": "Wembley Stadium, London, England",
    "notes": "Retained WBA (Super), IBF, WBO, and IBO heavyweight titles"
  },
  {
    "number": 21,
    "result": "Win",
    "record": "21–0",
    "opponent": "Joseph Parker",
    "type": "UD",
    "round": "12",
    "date": "31 Mar 2018",
    "location": "Principality Stadium, Cardiff, Wales",
    "notes": "Retained WBA (Super), IBF, and IBO heavyweight titles;Won WBO heavyweight title"
  },
  {
    "number": 20,
    "result": "Win",
    "record": "20–0",
    "opponent": "Carlos Takam",
    "type": "TKO",
    "round": "10 (12), 1:34",
    "date": "28 Oct 2017",
    "location": "Principality Stadium, Cardiff, Wales",
    "notes": "Retained WBA (Super), IBF, and IBO heavyweight titles"
  },
  {
    "number": 19,
    "result": "Win",
    "record": "19–0",
    "opponent": "Wladimir Klitschko",
    "type": "TKO",
    "round": "11 (12), 2:25",
    "date": "29 Apr 2017",
    "location": "Wembley Stadium, London, England",
    "notes": "Retained IBF heavyweight title;Won vacant WBA (Super) and IBO heavyweight titles"
  },
  {
    "number": 18,
    "result": "Win",
    "record": "18–0",
    "opponent": "Éric Molina",
    "type": "TKO",
    "round": "3 (12), 2:02",
    "date": "10 Dec 2016",
    "location": "Manchester Arena, Manchester, England",
    "notes": "Retained IBF heavyweight title"
  },
  {
    "number": 17,
    "result": "Win",
    "record": "17–0",
    "opponent": "Dominic Breazeale",
    "type": "TKO",
    "round": "7 (12), 1:01",
    "date": "25 Jun 2016",
    "location": "The O2 Arena, London, England",
    "notes": "Retained IBF heavyweight title"
  },
  {
    "number": 16,
    "result": "Win",
    "record": "16–0",
    "opponent": "Charles Martin",
    "type": "KO",
    "round": "2 (12), 1:32",
    "date": "9 Apr 2016",
    "location": "The O2 Arena, London, England",
    "notes": "Won IBF heavyweight title"
  },
  {
    "number": 15,
    "result": "Win",
    "record": "15–0",
    "opponent": "Dillian Whyte",
    "type": "KO",
    "round": "7 (12), 1:27",
    "date": "12 Dec 2015",
    "location": "The O2 Arena, London, England",
    "notes": "Retained WBC International and Commonwealth heavyweight titles;Won vacant British heavyweight title"
  },
  {
    "number": 14,
    "result": "Win",
    "record": "14–0",
    "opponent": "Gary Cornish",
    "type": "TKO",
    "round": "1 (12), 1:37",
    "date": "12 Sep 2015",
    "location": "The O2 Arena, London, England",
    "notes": "Retained WBC International heavyweight title;Won vacant Commonwealth heavyweight title"
  },
  {
    "number": 13,
    "result": "Win",
    "record": "13–0",
    "opponent": "Kevin Johnson",
    "type": "TKO",
    "round": "2 (10), 1:22",
    "date": "30 May 2015",
    "location": "The O2 Arena, London, England",
    "notes": "Retained WBC International heavyweight title"
  },
  {
    "number": 12,
    "result": "Win",
    "record": "12–0",
    "opponent": "Raphael Zumbano Love",
    "type": "TKO",
    "round": "2 (8), 1:21",
    "date": "9 May 2015",
    "location": "Barclaycard Arena, Birmingham, England",
    "notes": ""
  },
  {
    "number": 11,
    "result": "Win",
    "record": "11–0",
    "opponent": "Jason Gavern",
    "type": "KO",
    "round": "3 (8), 1:21",
    "date": "4 Apr 2015",
    "location": "Metro Radio Arena, Newcastle, England",
    "notes": ""
  },
  {
    "number": 10,
    "result": "Win",
    "record": "10–0",
    "opponent": "Michael Sprott",
    "type": "TKO",
    "round": "1 (10), 1:26",
    "date": "22 Nov 2014",
    "location": "Echo Arena, Liverpool, England",
    "notes": ""
  },
  {
    "number": 9,
    "result": "Win",
    "record": "9–0",
    "opponent": "Denis Bakhtov",
    "type": "TKO",
    "round": "2 (10), 1:00",
    "date": "11 Oct 2014",
    "location": "The O2 Arena, London, England",
    "notes": "Won vacant WBC International heavyweight title"
  },
  {
    "number": 8,
    "result": "Win",
    "record": "8–0",
    "opponent": "Konstantin Airich",
    "type": "TKO",
    "round": "3 (8), 1:16",
    "date": "13 Sep 2014",
    "location": "Phones 4u Arena, Manchester, England",
    "notes": ""
  },
  {
    "number": 7,
    "result": "Win",
    "record": "7–0",
    "opponent": "Matt Skelton",
    "type": "TKO",
    "round": "2 (6), 2:33",
    "date": "12 Jul 2014",
    "location": "Echo Arena, Liverpool, England",
    "notes": ""
  },
  {
    "number": 6,
    "result": "Win",
    "record": "6–0",
    "opponent": "Matt Legg",
    "type": "KO",
    "round": "1 (6), 1:23",
    "date": "31 May 2014",
    "location": "Wembley Stadium, London, England",
    "notes": ""
  },
  {
    "number": 5,
    "result": "Win",
    "record": "5–0",
    "opponent": "Hector Avila",
    "type": "KO",
    "round": "1 (6), 2:14",
    "date": "1 Mar 2014",
    "location": "Exhibition and Conference Centre, Glasgow, Scotland",
    "notes": ""
  },
  {
    "number": 4,
    "result": "Win",
    "record": "4–0",
    "opponent": "Dorian Darch",
    "type": "TKO",
    "round": "2 (6), 0:51",
    "date": "1 Feb 2014",
    "location": "Motorpoint Arena, Cardiff, Wales",
    "notes": ""
  },
  {
    "number": 3,
    "result": "Win",
    "record": "3–0",
    "opponent": "Hrvoje Kisicek",
    "type": "TKO",
    "round": "2 (6), 1:38",
    "date": "14 Nov 2013",
    "location": "York Hall, London, England",
    "notes": ""
  },
  {
    "number": 2,
    "result": "Win",
    "record": "2–0",
    "opponent": "Paul Butlin",
    "type": "TKO",
    "round": "2 (6), 0:50",
    "date": "26 Oct 2013",
    "location": "Motorpoint Arena, Sheffield, England",
    "notes": ""
  },
  {
    "number": 1,
    "result": "Win",
    "record": "1–0",
    "opponent": "Emanuele Leo",
    "type": "TKO",
    "round": "1 (6), 2:47",
    "date": "5 Oct 2013",
    "location": "The O2 Arena, London, England",
    "notes": ""
  }
]
