[
  {
    "Number": 38,
    "Result": "Draw",
    "Record": "35–2–1",
    "Opponent": "Michael Hunter",
    "Type": "SD",
    "Round": "12",
    "Date": "7 Dec 2019",
    "Location": "Diriyah Arena, Diriyah, Saudi Arabia",
    "Notes": ""
  },
  {
    "Number": 37,
    "Result": "Win",
    "Record": "35–2",
    "Opponent": "Hughie Fury",
    "Type": "UD",
    "Round": "12",
    "Date": "31 Aug 2019",
    "Location": "The O2 Arena, London, England",
    "Notes": "Won vacant WBA International heavyweight title"
  },
  {
    "Number": 36,
    "Result": "Loss",
    "Record": "34–2",
    "Opponent": "Anthony Joshua",
    "Type": "TKO",
    "Round": "7 (12), 1:59",
    "Date": "22 Sep 2018",
    "Location": "Wembley Stadium, London, England",
    "Notes": "For WBA (Super), IBF, WBO, and IBO heavyweight titles"
  },
  {
    "Number": 35,
    "Result": "Win",
    "Record": "34–1",
    "Opponent": "David Price",
    "Type": "KO",
    "Round": "5 (12), 1:02",
    "Date": "31 Mar 2018",
    "Location": "Principality Stadium, Cardiff, Wales",
    "Notes": "Retained WBA Inter-Continental and WBO International heavyweight titles"
  },
  {
    "Number": 34,
    "Result": "Win",
    "Record": "33–1",
    "Opponent": "Christian Hammer",
    "Type": "UD",
    "Round": "12",
    "Date": "15 Dec 2017",
    "Location": "Palace of Sporting Games, Yekaterinburg, Russia",
    "Notes": "Retained WBO International heavyweight title;Won vacant WBA Inter-Continental heavyweight title"
  },
  {
    "Number": 33,
    "Result": "Win",
    "Record": "32–1",
    "Opponent": "Andriy Rudenko",
    "Type": "UD",
    "Round": "12",
    "Date": "1 Jul 2017",
    "Location": "Luzhniki Palace of Sports, Moscow, Russia",
    "Notes": "Won vacant WBA Continental (Europe) and WBO International heavyweight titles"
  },
  {
    "Number": 32,
    "Result": "Win",
    "Record": "31–1",
    "Opponent": "Johann Duhaupas",
    "Type": "KO",
    "Round": "6 (10), 2:59",
    "Date": "17 Dec 2016",
    "Location": "IEC Expo, Yekaterinburg, Russia",
    "Notes": ""
  },
  {
    "Number": 31,
    "Result": "Win",
    "Record": "30–1",
    "Opponent": "Mariusz Wach",
    "Type": "TKO",
    "Round": "12 (12) 0:50",
    "Date": "4 Nov 2015",
    "Location": "TatNeft Arena, Kazan, Russia",
    "Notes": "Retained WBC Silver heavyweight title"
  },
  {
    "Number": 30,
    "Result": "Win",
    "Record": "29–1",
    "Opponent": "Mike Perez",
    "Type": "TKO",
    "Round": "1 (12), 1:31",
    "Date": "22 May 2015",
    "Location": "Luzhniki Palace of Sports, Moscow, Russia",
    "Notes": "Retained WBC Silver heavyweight title"
  },
  {
    "Number": 29,
    "Result": "Win",
    "Record": "28–1",
    "Opponent": "Carlos Takam",
    "Type": "KO",
    "Round": "10 (12), 0:54",
    "Date": "24 Oct 2014",
    "Location": "Luzhniki Palace of Sports, Moscow, Russia",
    "Notes": "Won WBC Silver heavyweight title"
  },
  {
    "Number": 28,
    "Result": "Win",
    "Record": "27–1",
    "Opponent": "Manuel Charr",
    "Type": "KO",
    "Round": "7 (12), 1:09",
    "Date": "30 May 2014",
    "Location": "Luzhniki Palace of Sports, Moscow, Russia",
    "Notes": "Won WBC International heavyweight title"
  },
  {
    "Number": 27,
    "Result": "Loss",
    "Record": "26–1",
    "Opponent": "Wladimir Klitschko",
    "Type": "UD",
    "Round": "12",
    "Date": "5 Oct 2013",
    "Location": "Olympic Indoor Arena, Moscow, Russia",
    "Notes": "Lost WBA (Regular) heavyweight title;For IBF, WBO, IBO, The Ring, and lineal heavyweight titles"
  },
  {
    "Number": 26,
    "Result": "Win",
    "Record": "26–0",
    "Opponent": "Andrzej Wawrzyk",
    "Type": "TKO",
    "Round": "3 (12), 2:28",
    "Date": "17 May 2013",
    "Location": "Crocus City Hall, Krasnogorsk, Russia",
    "Notes": "Retained WBA (Regular) heavyweight title"
  },
  {
    "Number": 25,
    "Result": "Win",
    "Record": "25–0",
    "Opponent": "Hasim Rahman",
    "Type": "TKO",
    "Round": "2 (12), 1:46",
    "Date": "29 Sep 2012",
    "Location": "Alsterdorfer Sporthalle, Hamburg, Germany",
    "Notes": "Retained WBA (Regular) heavyweight title"
  },
  {
    "Number": 24,
    "Result": "Win",
    "Record": "24–0",
    "Opponent": "Marco Huck",
    "Type": "MD",
    "Round": "12",
    "Date": "25 Feb 2012",
    "Location": "Porsche-Arena, Stuttgart, Germany",
    "Notes": "Retained WBA (Regular) heavyweight title"
  },
  {
    "Number": 23,
    "Result": "Win",
    "Record": "23–0",
    "Opponent": "Cedric Boswell",
    "Type": "KO",
    "Round": "8 (12), 2:58",
    "Date": "3 Dec 2011",
    "Location": "Hartwall Arena, Helsinki, Finland",
    "Notes": "Retained WBA (Regular) heavyweight title"
  },
  {
    "Number": 22,
    "Result": "Win",
    "Record": "22–0",
    "Opponent": "Ruslan Chagaev",
    "Type": "UD",
    "Round": "12",
    "Date": "27 Aug 2011",
    "Location": "Messe, Erfurt, Germany",
    "Notes": "Won vacant WBA (Regular) heavyweight title"
  },
  {
    "Number": 21,
    "Result": "Win",
    "Record": "21–0",
    "Opponent": "Nicolai Firtha",
    "Type": "UD",
    "Round": "10",
    "Date": "18 Dec 2010",
    "Location": "Max-Schmeling-Halle, Berlin, Germany",
    "Notes": ""
  },
  {
    "Number": 20,
    "Result": "Win",
    "Record": "20–0",
    "Opponent": "Teke Oruh",
    "Type": "KO",
    "Round": "5 (10), 2:57",
    "Date": "16 Oct 2010",
    "Location": "Olimpyskiy Sports Palace, Chekhov, Russia",
    "Notes": ""
  },
  {
    "Number": 19,
    "Result": "Win",
    "Record": "19–0",
    "Opponent": "Javier Mora",
    "Type": "TKO",
    "Round": "5 (10), 0:50",
    "Date": "13 Mar 2010",
    "Location": "Max-Schmeling-Halle, Berlin, Germany",
    "Notes": ""
  },
  {
    "Number": 18,
    "Result": "Win",
    "Record": "18–0",
    "Opponent": "Leo Nolan",
    "Type": "KO",
    "Round": "3 (10), 2:33",
    "Date": "5 Dec 2009",
    "Location": "MHP Arena, Ludwigsburg, Germany",
    "Notes": ""
  },
  {
    "Number": 17,
    "Result": "Win",
    "Record": "17–0",
    "Opponent": "Jason Estrada",
    "Type": "UD",
    "Round": "10",
    "Date": "4 Apr 2009",
    "Location": "Burg-Wächter Castello, Düsseldorf, Germany",
    "Notes": ""
  },
  {
    "Number": 16,
    "Result": "Win",
    "Record": "16–0",
    "Opponent": "Taurus Sykes",
    "Type": "KO",
    "Round": "4 (10), 1:43",
    "Date": "19 Jul 2008",
    "Location": "Olimpyskiy Sports Palace, Chekhov, Russia",
    "Notes": ""
  },
  {
    "Number": 15,
    "Result": "Win",
    "Record": "15–0",
    "Opponent": "Eddie Chambers",
    "Type": "UD",
    "Round": "12",
    "Date": "26 Jan 2008",
    "Location": "Tempodrom, Berlin, Germany",
    "Notes": ""
  },
  {
    "Number": 14,
    "Result": "Win",
    "Record": "14–0",
    "Opponent": "Chris Byrd",
    "Type": "TKO",
    "Round": "11 (12), 1:52",
    "Date": "27 Oct 2007",
    "Location": "Messe, Erfurt, Germany",
    "Notes": ""
  },
  {
    "Number": 13,
    "Result": "Win",
    "Record": "13–0",
    "Opponent": "Larry Donald",
    "Type": "UD",
    "Round": "10",
    "Date": "30 Jun 2007",
    "Location": "Olympic Indoor Arena, Moscow, Russia",
    "Notes": ""
  },
  {
    "Number": 12,
    "Result": "Win",
    "Record": "12–0",
    "Opponent": "Patrice L'Heureux",
    "Type": "KO",
    "Round": "2 (10), 1:02",
    "Date": "26 May 2007",
    "Location": "Jako Arena, Bamberg, Germany",
    "Notes": ""
  },
  {
    "Number": 11,
    "Result": "Win",
    "Record": "11–0",
    "Opponent": "David Bostice",
    "Type": "TKO",
    "Round": "2 (10), 2:57",
    "Date": "3 Mar 2007",
    "Location": "StadtHalle, Rostock, Germany",
    "Notes": ""
  },
  {
    "Number": 10,
    "Result": "Win",
    "Record": "10–0",
    "Opponent": "Imamu Mayfield",
    "Type": "TKO",
    "Round": "3 (10)",
    "Date": "10 Dec 2006",
    "Location": "Olympic Indoor Arena, Moscow, Russia",
    "Notes": ""
  },
  {
    "Number": 9,
    "Result": "Win",
    "Record": "9–0",
    "Opponent": "Ed Mahone",
    "Type": "TKO",
    "Round": "5 (8), 2:05",
    "Date": "23 Sep 2006",
    "Location": "Rittal Arena, Wetzlar, Germany",
    "Notes": ""
  },
  {
    "Number": 8,
    "Result": "Win",
    "Record": "8–0",
    "Opponent": "Livin Castillo",
    "Type": "TKO",
    "Round": "4 (8), 2:45",
    "Date": "3 Jun 2006",
    "Location": "TUI Arena, Hanover, Germany",
    "Notes": ""
  },
  {
    "Number": 7,
    "Result": "Win",
    "Record": "7–0",
    "Opponent": "Friday Ahunanya",
    "Type": "UD",
    "Round": "6",
    "Date": "22 Apr 2006",
    "Location": "SAP Arena, Mannheim, Germany",
    "Notes": ""
  },
  {
    "Number": 6,
    "Result": "Win",
    "Record": "6–0",
    "Opponent": "Richard Bango",
    "Type": "KO",
    "Round": "2 (6), 2:20",
    "Date": "4 Mar 2006",
    "Location": "EWE Arena, Oldenburg, Germany",
    "Notes": ""
  },
  {
    "Number": 5,
    "Result": "Win",
    "Record": "5–0",
    "Opponent": "Willie Chapman",
    "Type": "TKO",
    "Round": "5 (6), 2:21",
    "Date": "17 Dec 2005",
    "Location": "Max-Schmeling-Halle, Berlin, Germany",
    "Notes": ""
  },
  {
    "Number": 4,
    "Result": "Win",
    "Record": "4–0",
    "Opponent": "Stephane Tessier",
    "Type": "UD",
    "Round": "4",
    "Date": "12 Nov 2005",
    "Location": "Alsterdorfer Sporthalle, Hamburg, Germany",
    "Notes": ""
  },
  {
    "Number": 3,
    "Result": "Win",
    "Record": "3–0",
    "Opponent": "John Castle",
    "Type": "RTD",
    "Round": "1 (4), 3:00",
    "Date": "1 Oct 2005",
    "Location": "EWE Arena, Oldenburg, Germany",
    "Notes": ""
  },
  {
    "Number": 2,
    "Result": "Win",
    "Record": "2–0",
    "Opponent": "Cerrone Fox",
    "Type": "TKO",
    "Round": "4 (4), 2:37",
    "Date": "3 Sep 2005",
    "Location": "Internationales Congress Centrum, Berlin, Germany",
    "Notes": ""
  },
  {
    "Number": 1,
    "Result": "Win",
    "Record": "1–0",
    "Opponent": "Muhammad Ali Durmaz",
    "Type": "TKO",
    "Round": "2 (4), 1:23",
    "Date": "11 Jun 2005",
    "Location": "BigBox, Kempten, Germany",
    "Notes": ""
  }
]
